demo/migrations/0001_initial.py
demo/migrations/__init__.py
django_dynamic_model_validation/__init__.py
django_dynamic_model_validation/settings.py
django_dynamic_model_validation/wsgi.py
dynamic_validator/__init__.py
dynamic_validator/apps.py
dynamic_validator/tests.py
dynamic_validator/field_validation/__init__.py
dynamic_validator/field_validation/validator.py
django_dynamic_model_validation-1.0.0.dist-info/LICENSE-APACHE
django_dynamic_model_validation-1.0.0.dist-info/LICENSE-MIT
django_dynamic_model_validation-1.0.0.dist-info/METADATA
django_dynamic_model_validation-1.0.0.dist-info/WHEEL
django_dynamic_model_validation-1.0.0.dist-info/top_level.txt
django_dynamic_model_validation-1.0.0.dist-info/RECORD
