Metadata-Version: 2.1
Name: django-dynamic-model-validation
Version: 1.0.0
Summary: Extra django model validation.
Home-page: https://github.com/jackton1/django-dynamic-model-validation.git
Author: Tonye Jack
Author-email: jtonye@ymail.com
Maintainer: Tonye Jack
Maintainer-email: jtonye@ymail.com
License: MIT/Apache-2.0
Keywords: django,model validation,django models,django object validation,field validation,conditional validation,cross field validation,django validation,django validators,django custom validation
Platform: UNKNOWN
Classifier: Development Status :: 5 - Production/Stable
Classifier: Intended Audience :: Developers
Classifier: License :: OSI Approved :: MIT License
Classifier: License :: OSI Approved :: Apache Software License
Classifier: Natural Language :: English
Classifier: Topic :: Internet :: WWW/HTTP
Classifier: Operating System :: OS Independent
Classifier: Programming Language :: Python :: 2.7
Classifier: Programming Language :: Python :: 3.5
Classifier: Programming Language :: Python :: 3.6
Classifier: Programming Language :: Python :: 3.7
Classifier: Programming Language :: Python :: 3.8
Classifier: Programming Language :: Python :: 3.9
Classifier: Programming Language :: Python :: Implementation :: CPython
Classifier: Programming Language :: Python :: Implementation :: PyPy
Classifier: Framework :: Django :: 1.11
Classifier: Framework :: Django :: 2.0
Classifier: Framework :: Django :: 2.1
Classifier: Framework :: Django :: 2.2
Classifier: Framework :: Django :: 3.0
Classifier: Framework :: Django :: 3.1
Requires-Python: >=2.6
Requires-Dist: future
Requires-Dist: six
Provides-Extra: deploy
Requires-Dist: readme-renderer[md] ; extra == 'deploy'
Requires-Dist: bump2version (==0.5.11) ; extra == 'deploy'
Provides-Extra: development
Requires-Dist: Django (>=1.11.18) ; extra == 'development'
Requires-Dist: pip-tools ; extra == 'development'
Requires-Dist: check-manifest ; extra == 'development'
Requires-Dist: future ; extra == 'development'
Requires-Dist: six ; extra == 'development'
Requires-Dist: tox ; extra == 'development'
Requires-Dist: pytest-django ; extra == 'development'
Requires-Dist: pluggy (>=0.7) ; extra == 'development'
Requires-Dist: mock ; extra == 'development'
Requires-Dist: codacy-coverage ; extra == 'development'
Requires-Dist: flake8 ; extra == 'development'
Requires-Dist: yamllint ; extra == 'development'
Requires-Dist: isort ; extra == 'development'
Provides-Extra: lint
Requires-Dist: flake8 ; extra == 'lint'
Requires-Dist: yamllint ; extra == 'lint'
Requires-Dist: isort ; extra == 'lint'
Provides-Extra: test
Requires-Dist: tox ; extra == 'test'
Requires-Dist: pytest-django ; extra == 'test'
Requires-Dist: pluggy (>=0.7) ; extra == 'test'
Requires-Dist: mock ; extra == 'test'
Requires-Dist: codacy-coverage ; extra == 'test'
Provides-Extra: tox
Requires-Dist: Django (>=1.11.18) ; extra == 'tox'
Requires-Dist: pip-tools ; extra == 'tox'
Requires-Dist: check-manifest ; extra == 'tox'
